epigraphdbpy/__init__.py
epigraphdbpy/api.py
epigraphdbpy/constants.py
epigraphdbpy/queries.py
epigraphdbpy/to_networkx.py
tests/__init__.py
tests/test_api.py
tests/test_queries.py
epigraphdbpy-0.0.1.dist-info/LICENSE
epigraphdbpy-0.0.1.dist-info/METADATA
epigraphdbpy-0.0.1.dist-info/WHEEL
epigraphdbpy-0.0.1.dist-info/top_level.txt
epigraphdbpy-0.0.1.dist-info/RECORD
