Metadata-Version: 2.1
Name: epigraphdbpy
Version: 0.0.1
Summary: Python interface to EpiGraphDB API
Home-page: https://mrcieu.github.io/epigraphdbpy/
Author: Tom Gaunt
Author-email: tom@biocompute.org.uk
License: UNKNOWN
Platform: UNKNOWN
Classifier: Programming Language :: Python :: 3
Classifier: License :: OSI Approved :: MIT License
Classifier: Operating System :: OS Independent
Requires-Python: >=3.6
Requires-Dist: requests
Requires-Dist: retry
